nikol/__init__.py
nikol/core/__init__.py
nikol/core/config.py
nikol/core/help.py
nikol/core/init.py
nikol/main/__init__.py
nikol/main/cli.py
nikol/main/command.py
nikol/main/commander.py
nikol/main/command/__init__.py
nikol/main/command/config.py
nikol/main/command/conv.py
nikol/main/command/eval.py
nikol/main/command/help.py
nikol/main/command/init.py
nikol/main/command/patch.py
nikol/main/command/please.py
nikol/main/command/say.py
nikol/misc/__init__.py
nikol/misc/say.py
nikol/table/__init__.py
nikol/table/object.py
nikol/table/reader.py
nikol/table/row.py
nikol/table/tag.py
nikol/update/__init__.py
nikol/update/update.py
nikol/valid/__init__.py
nikol/valid/begend.py
nikol/valid/cr.py
nikol/valid/dp.py
nikol/valid/ls.py
nikol/valid/mp.py
nikol/valid/ne.py
nikol/valid/sentence.py
nikol/valid/sr.py
nikol/valid/util.py
nikol/valid/word.py
nikol/valid/za.py
nikol-0.3.1.dist-info/LICENSE
nikol-0.3.1.dist-info/METADATA
nikol-0.3.1.dist-info/WHEEL
nikol-0.3.1.dist-info/entry_points.txt
nikol-0.3.1.dist-info/top_level.txt
nikol-0.3.1.dist-info/RECORD
