Metadata-Version: 2.1
Name: nikol
Version: 0.3.1
Summary: nikol
Home-page: https://github.com/nikltk/nikol
Author: 
Author-email: 
License: UNKNOWN
Platform: UNKNOWN
Classifier: Programming Language :: Python :: 3
Classifier: License :: OSI Approved :: GNU General Public License v3 or later (GPLv3+)
Classifier: Operating System :: OS Independent
Requires-Python: >=3.8
License-File: LICENSE
Requires-Dist: koltk (>=0.1.0)
